{"v":"5.5.5","fr":29.9700012207031,"ip":0,"op":60.0000024438501,"w":343,"h":340,"nm":"miruho_WS01","ddd":0,"assets":[],"layers":[{"ddd":0,"ind":1,"ty":4,"nm":"シェイプレイヤー 1","sr":1,"ks":{"o":{"a":0,"k":100,"ix":11},"r":{"a":0,"k":0,"ix":10},"p":{"a":0,"k":[1.5,-7,0],"ix":2},"a":{"a":0,"k":[0,0,0],"ix":1},"s":{"a":0,"k":[100,100,100],"ix":6}},"ao":0,"shapes":[{"ty":"gr","it":[{"ind":0,"ty":"sh","ix":1,"ks":{"a":0,"k":{"i":[[0,0],[0,0],[0,0]],"o":[[0,0],[0,0],[0,0]],"v":[[5.236,10.39],[10.253,-10.39],[-10.254,-4.348]],"c":true},"ix":2},"nm":"パス 1","mn":"ADBE Vector Shape - Group","hd":false},{"ty":"fl","c":{"a":0,"k":[0.435000011968,0.894000004787,0.74900004069,1],"ix":4},"o":{"a":0,"k":100,"ix":5},"r":1,"bm":0,"nm":"塗り 1","mn":"ADBE Vector Graphic - Fill","hd":false},{"ty":"tr","p":{"a":0,"k":[270.131,54.508],"ix":2},"a":{"a":0,"k":[-10.35,10.371],"ix":1},"s":{"a":1,"k":[{"i":{"x":[0.582,0.582],"y":[2.412,2.412]},"o":{"x":[0.82,0.82],"y":[0.088,0.088]},"t":28,"s":[0,0]},{"t":34.0000013848484,"s":[100,100]}],"ix":3},"r":{"a":0,"k":0,"ix":6},"o":{"a":0,"k":100,"ix":7},"sk":{"a":0,"k":0,"ix":4},"sa":{"a":0,"k":0,"ix":5},"nm":"トランスフォーム"}],"nm":"グループ 1","np":2,"cix":2,"bm":0,"ix":1,"mn":"ADBE Vector Group","hd":false},{"ty":"gr","it":[{"ind":0,"ty":"sh","ix":1,"ks":{"a":0,"k":{"i":[[0,0],[-25.358,25.438]],"o":[[89.042,0],[0,0]],"v":[[-91.746,42.625],[91.746,-42.625]],"c":false},"ix":2},"nm":"パス 1","mn":"ADBE Vector Shape - Group","hd":false},{"ty":"tm","s":{"a":0,"k":0,"ix":1},"e":{"a":1,"k":[{"i":{"x":[0.994],"y":[0.614]},"o":{"x":[0.81],"y":[0]},"t":0,"s":[0]},{"t":30.0000012219251,"s":[100]}],"ix":2},"o":{"a":0,"k":0,"ix":3},"m":1,"ix":2,"nm":"パスのトリミング 1","mn":"ADBE Vector Filter - Trim","hd":false},{"ty":"st","c":{"a":0,"k":[0.435000011968,0.894000004787,0.74900004069,1],"ix":3},"o":{"a":0,"k":100,"ix":4},"w":{"a":0,"k":4.288,"ix":5},"lc":2,"lj":2,"bm":0,"nm":"線 1","mn":"ADBE Vector Graphic - Stroke","hd":false},{"ty":"tr","p":{"a":0,"k":[188.478,87.605],"ix":2},"a":{"a":0,"k":[0,0],"ix":1},"s":{"a":0,"k":[100,100],"ix":3},"r":{"a":0,"k":0,"ix":6},"o":{"a":0,"k":100,"ix":7},"sk":{"a":0,"k":0,"ix":4},"sa":{"a":0,"k":0,"ix":5},"nm":"トランスフォーム"}],"nm":"グループ 2","np":3,"cix":2,"bm":0,"ix":2,"mn":"ADBE Vector Group","hd":false}],"ip":0,"op":60.0000024438501,"st":0,"bm":0},{"ddd":0,"ind":2,"ty":4,"nm":"シェイプレイヤー 2","sr":1,"ks":{"o":{"a":0,"k":100,"ix":11},"r":{"a":0,"k":0,"ix":10},"p":{"a":0,"k":[200.5,191.5,0],"ix":2},"a":{"a":0,"k":[200,202,0],"ix":1},"s":{"a":1,"k":[{"i":{"x":[0.629,0.99,0.667],"y":[1,-0.11,1]},"o":{"x":[0.333,0.333,0.333],"y":[0,0,0]},"t":0,"s":[100,0,100]},{"t":30.0000012219251,"s":[100,100,100]}],"ix":6}},"ao":0,"shapes":[{"ty":"gr","it":[{"ind":0,"ty":"sh","ix":1,"ks":{"a":0,"k":{"i":[[0,0],[0,0],[0,0],[0,0]],"o":[[0,0],[0,0],[0,0],[0,0]],"v":[[5,70.297],[-5,70.297],[-5,-70.297],[5,-70.297]],"c":true},"ix":2},"nm":"パス 1","mn":"ADBE Vector Shape - Group","hd":false},{"ty":"fl","c":{"a":0,"k":[0.894000004787,0.435000011968,0.435000011968,1],"ix":4},"o":{"a":0,"k":100,"ix":5},"r":1,"bm":0,"nm":"塗り 1","mn":"ADBE Vector Graphic - Fill","hd":false},{"ty":"tr","p":{"a":0,"k":[291.232,130.23],"ix":2},"a":{"a":0,"k":[0,0],"ix":1},"s":{"a":0,"k":[100,100],"ix":3},"r":{"a":0,"k":0,"ix":6},"o":{"a":0,"k":100,"ix":7},"sk":{"a":0,"k":0,"ix":4},"sa":{"a":0,"k":0,"ix":5},"nm":"トランスフォーム"}],"nm":"グループ 3","np":2,"cix":2,"bm":0,"ix":1,"mn":"ADBE Vector Group","hd":false},{"ty":"gr","it":[{"ind":0,"ty":"sh","ix":1,"ks":{"a":0,"k":{"i":[[0,0],[0,0],[0,0],[0,0]],"o":[[0,0],[0,0],[0,0],[0,0]],"v":[[5,50.75],[-5,50.75],[-5,-50.75],[5,-50.75]],"c":true},"ix":2},"nm":"パス 1","mn":"ADBE Vector Shape - Group","hd":false},{"ty":"fl","c":{"a":0,"k":[0.972999961703,0.948999980852,0.455000005984,1],"ix":4},"o":{"a":0,"k":100,"ix":5},"r":1,"bm":0,"nm":"塗り 1","mn":"ADBE Vector Graphic - Fill","hd":false},{"ty":"tr","p":{"a":0,"k":[260.732,149.777],"ix":2},"a":{"a":0,"k":[0,0],"ix":1},"s":{"a":0,"k":[100,100],"ix":3},"r":{"a":0,"k":0,"ix":6},"o":{"a":0,"k":100,"ix":7},"sk":{"a":0,"k":0,"ix":4},"sa":{"a":0,"k":0,"ix":5},"nm":"トランスフォーム"}],"nm":"グループ 4","np":2,"cix":2,"bm":0,"ix":2,"mn":"ADBE Vector Group","hd":false},{"ty":"gr","it":[{"ind":0,"ty":"sh","ix":1,"ks":{"a":0,"k":{"i":[[0,0],[0,0],[0,0],[0,0]],"o":[[0,0],[0,0],[0,0],[0,0]],"v":[[5,37.25],[-5,37.25],[-5,-37.25],[5,-37.25]],"c":true},"ix":2},"nm":"パス 1","mn":"ADBE Vector Shape - Group","hd":false},{"ty":"fl","c":{"a":0,"k":[0.972999961703,0.948999980852,0.455000005984,1],"ix":4},"o":{"a":0,"k":100,"ix":5},"r":1,"bm":0,"nm":"塗り 1","mn":"ADBE Vector Graphic - Fill","hd":false},{"ty":"tr","p":{"a":0,"k":[230.232,163.277],"ix":2},"a":{"a":0,"k":[0,0],"ix":1},"s":{"a":0,"k":[100,100],"ix":3},"r":{"a":0,"k":0,"ix":6},"o":{"a":0,"k":100,"ix":7},"sk":{"a":0,"k":0,"ix":4},"sa":{"a":0,"k":0,"ix":5},"nm":"トランスフォーム"}],"nm":"グループ 5","np":2,"cix":2,"bm":0,"ix":3,"mn":"ADBE Vector Group","hd":false},{"ty":"gr","it":[{"ind":0,"ty":"sh","ix":1,"ks":{"a":0,"k":{"i":[[0,0],[0,0],[0,0],[0,0]],"o":[[0,0],[0,0],[0,0],[0,0]],"v":[[5,29.75],[-5,29.75],[-5,-29.75],[5,-29.75]],"c":true},"ix":2},"nm":"パス 1","mn":"ADBE Vector Shape - Group","hd":false},{"ty":"fl","c":{"a":0,"k":[0.972999961703,0.948999980852,0.455000005984,1],"ix":4},"o":{"a":0,"k":100,"ix":5},"r":1,"bm":0,"nm":"塗り 1","mn":"ADBE Vector Graphic - Fill","hd":false},{"ty":"tr","p":{"a":0,"k":[199.732,170.777],"ix":2},"a":{"a":0,"k":[0,0],"ix":1},"s":{"a":0,"k":[100,100],"ix":3},"r":{"a":0,"k":0,"ix":6},"o":{"a":0,"k":100,"ix":7},"sk":{"a":0,"k":0,"ix":4},"sa":{"a":0,"k":0,"ix":5},"nm":"トランスフォーム"}],"nm":"グループ 6","np":2,"cix":2,"bm":0,"ix":4,"mn":"ADBE Vector Group","hd":false},{"ty":"gr","it":[{"ind":0,"ty":"sh","ix":1,"ks":{"a":0,"k":{"i":[[0,0],[0,0],[0,0],[0,0]],"o":[[0,0],[0,0],[0,0],[0,0]],"v":[[5,23.25],[-5,23.25],[-5,-23.25],[5,-23.25]],"c":true},"ix":2},"nm":"パス 1","mn":"ADBE Vector Shape - Group","hd":false},{"ty":"fl","c":{"a":0,"k":[0.19199999641,0.635000011968,1,1],"ix":4},"o":{"a":0,"k":100,"ix":5},"r":1,"bm":0,"nm":"塗り 1","mn":"ADBE Vector Graphic - Fill","hd":false},{"ty":"tr","p":{"a":0,"k":[169.232,177.277],"ix":2},"a":{"a":0,"k":[0,0],"ix":1},"s":{"a":0,"k":[100,100],"ix":3},"r":{"a":0,"k":0,"ix":6},"o":{"a":0,"k":100,"ix":7},"sk":{"a":0,"k":0,"ix":4},"sa":{"a":0,"k":0,"ix":5},"nm":"トランスフォーム"}],"nm":"グループ 7","np":2,"cix":2,"bm":0,"ix":5,"mn":"ADBE Vector Group","hd":false},{"ty":"gr","it":[{"ind":0,"ty":"sh","ix":1,"ks":{"a":0,"k":{"i":[[0,0],[0,0],[0,0],[0,0]],"o":[[0,0],[0,0],[0,0],[0,0]],"v":[[5,16.75],[-5,16.75],[-5,-16.75],[5,-16.75]],"c":true},"ix":2},"nm":"パス 1","mn":"ADBE Vector Shape - Group","hd":false},{"ty":"fl","c":{"a":0,"k":[0.19199999641,0.635000011968,1,1],"ix":4},"o":{"a":0,"k":100,"ix":5},"r":1,"bm":0,"nm":"塗り 1","mn":"ADBE Vector Graphic - Fill","hd":false},{"ty":"tr","p":{"a":0,"k":[138.732,183.777],"ix":2},"a":{"a":0,"k":[0,0],"ix":1},"s":{"a":0,"k":[100,100],"ix":3},"r":{"a":0,"k":0,"ix":6},"o":{"a":0,"k":100,"ix":7},"sk":{"a":0,"k":0,"ix":4},"sa":{"a":0,"k":0,"ix":5},"nm":"トランスフォーム"}],"nm":"グループ 8","np":2,"cix":2,"bm":0,"ix":6,"mn":"ADBE Vector Group","hd":false},{"ty":"gr","it":[{"ind":0,"ty":"sh","ix":1,"ks":{"a":0,"k":{"i":[[0,0],[0,0],[0,0],[0,0]],"o":[[0,0],[0,0],[0,0],[0,0]],"v":[[5,7.75],[-5,7.75],[-5,-7.75],[5,-7.75]],"c":true},"ix":2},"nm":"パス 1","mn":"ADBE Vector Shape - Group","hd":false},{"ty":"fl","c":{"a":0,"k":[0.19199999641,0.635000011968,1,1],"ix":4},"o":{"a":0,"k":100,"ix":5},"r":1,"bm":0,"nm":"塗り 1","mn":"ADBE Vector Graphic - Fill","hd":false},{"ty":"tr","p":{"a":0,"k":[108.232,192.777],"ix":2},"a":{"a":0,"k":[0,0],"ix":1},"s":{"a":0,"k":[100,100],"ix":3},"r":{"a":0,"k":0,"ix":6},"o":{"a":0,"k":100,"ix":7},"sk":{"a":0,"k":0,"ix":4},"sa":{"a":0,"k":0,"ix":5},"nm":"トランスフォーム"}],"nm":"グループ 9","np":2,"cix":2,"bm":0,"ix":7,"mn":"ADBE Vector Group","hd":false}],"ip":0,"op":60.0000024438501,"st":0,"bm":0},{"ddd":0,"ind":3,"ty":4,"nm":"miruho_WS01アウトライン","sr":1,"ks":{"o":{"a":0,"k":100,"ix":11},"r":{"a":0,"k":0,"ix":10},"p":{"a":0,"k":[171.5,170,0],"ix":2},"a":{"a":0,"k":[171.5,170,0],"ix":1},"s":{"a":0,"k":[100,100,100],"ix":6}},"ao":0,"shapes":[{"ty":"gr","it":[{"ind":0,"ty":"sh","ix":1,"ks":{"a":0,"k":{"i":[[0,0],[0,0],[0,0],[0,0],[0,0],[0,0],[0,0],[0,0],[0,0],[0,0]],"o":[[0,0],[0,0],[0,0],[0,0],[0,0],[0,0],[0,0],[0,0],[0,0],[0,0]],"v":[[-6.949,11.635],[-2.117,10.405],[-4.684,6.129],[0.148,4.896],[-2.419,0.625],[2.413,-0.608],[-0.154,-4.883],[4.678,-6.117],[2.115,-10.397],[6.949,-11.635]],"c":false},"ix":2},"nm":"パス 1","mn":"ADBE Vector Shape - Group","hd":false},{"ty":"st","c":{"a":0,"k":[0.054999998504,0.149000010771,0.246999987434,1],"ix":3},"o":{"a":0,"k":100,"ix":4},"w":{"a":0,"k":0.774,"ix":5},"lc":1,"lj":1,"ml":10,"bm":0,"nm":"線 1","mn":"ADBE Vector Graphic - Stroke","hd":false},{"ty":"tr","p":{"a":0,"k":[60.162,117.357],"ix":2},"a":{"a":0,"k":[0,0],"ix":1},"s":{"a":0,"k":[100,100],"ix":3},"r":{"a":0,"k":0,"ix":6},"o":{"a":0,"k":100,"ix":7},"sk":{"a":0,"k":0,"ix":4},"sa":{"a":0,"k":0,"ix":5},"nm":"トランスフォーム"}],"nm":"グループ 10","np":2,"cix":2,"bm":0,"ix":1,"mn":"ADBE Vector Group","hd":false},{"ty":"gr","it":[{"ind":0,"ty":"sh","ix":1,"ks":{"a":0,"k":{"i":[[0,0],[0,0],[0,0],[0,0],[0,0],[0,0],[0,0],[0,0],[0,0],[0,0]],"o":[[0,0],[0,0],[0,0],[0,0],[0,0],[0,0],[0,0],[0,0],[0,0],[0,0]],"v":[[7.84,16.115],[9.102,10.634],[3.605,9.432],[4.867,3.949],[-0.626,2.752],[0.635,-2.732],[-4.861,-3.934],[-3.601,-9.418],[-9.102,-10.626],[-7.844,-16.115]],"c":false},"ix":2},"nm":"パス 1","mn":"ADBE Vector Shape - Group","hd":false},{"ty":"st","c":{"a":0,"k":[0.054999998504,0.149000010771,0.246999987434,1],"ix":3},"o":{"a":0,"k":100,"ix":4},"w":{"a":0,"k":1,"ix":5},"lc":1,"lj":1,"ml":10,"bm":0,"nm":"線 1","mn":"ADBE Vector Graphic - Stroke","hd":false},{"ty":"tr","p":{"a":0,"k":[36.741,120.005],"ix":2},"a":{"a":0,"k":[0,0],"ix":1},"s":{"a":0,"k":[100,100],"ix":3},"r":{"a":0,"k":0,"ix":6},"o":{"a":0,"k":100,"ix":7},"sk":{"a":0,"k":0,"ix":4},"sa":{"a":0,"k":0,"ix":5},"nm":"トランスフォーム"}],"nm":"グループ 11","np":2,"cix":2,"bm":0,"ix":2,"mn":"ADBE Vector Group","hd":false},{"ty":"gr","it":[{"ind":0,"ty":"sh","ix":1,"ks":{"a":0,"k":{"i":[[0,0],[0.247,-0.492],[0,0],[-0.513,-0.2],[0,0],[-0.441,0.329],[0,0],[0.388,0.39],[0,0],[0.545,0.079]],"o":[[-0.544,-0.079],[0,0],[-0.247,0.492],[0,0],[0.513,0.2],[0,0],[0.441,-0.329],[0,0],[-0.387,-0.39],[0,0]],"v":[[-4.027,-5.052],[-5.466,-4.302],[-7.41,-0.44],[-6.927,0.817],[3.641,4.931],[5.375,4.696],[7.173,3.355],[7.269,2.048],[1.626,-3.623],[-0.069,-4.476]],"c":true},"ix":2},"nm":"パス 1","mn":"ADBE Vector Shape - Group","hd":false},{"ty":"fl","c":{"a":0,"k":[0.054999998504,0.149000010771,0.246999987434,1],"ix":4},"o":{"a":0,"k":100,"ix":5},"r":1,"bm":0,"nm":"塗り 1","mn":"ADBE Vector Graphic - Fill","hd":false},{"ty":"tr","p":{"a":0,"k":[89.508,317.784],"ix":2},"a":{"a":0,"k":[0,0],"ix":1},"s":{"a":0,"k":[100,100],"ix":3},"r":{"a":0,"k":0,"ix":6},"o":{"a":0,"k":100,"ix":7},"sk":{"a":0,"k":0,"ix":4},"sa":{"a":0,"k":0,"ix":5},"nm":"トランスフォーム"}],"nm":"グループ 12","np":2,"cix":2,"bm":0,"ix":3,"mn":"ADBE Vector Group","hd":false},{"ty":"gr","it":[{"ind":0,"ty":"sh","ix":1,"ks":{"a":0,"k":{"i":[[0,0],[0.247,-0.491],[0,0],[-0.513,-0.199],[0,0],[-0.441,0.328],[0,0],[0.388,0.389],[0,0],[0.544,0.079]],"o":[[-0.544,-0.079],[0,0],[-0.247,0.492],[0,0],[0.513,0.201],[0,0],[0.441,-0.328],[0,0],[-0.388,-0.39],[0,0]],"v":[[-4.027,-5.052],[-5.466,-4.303],[-7.41,-0.44],[-6.927,0.816],[3.641,4.93],[5.375,4.696],[7.173,3.354],[7.269,2.048],[1.626,-3.623],[-0.069,-4.476]],"c":true},"ix":2},"nm":"パス 1","mn":"ADBE Vector Shape - Group","hd":false},{"ty":"fl","c":{"a":0,"k":[0.054999998504,0.149000010771,0.246999987434,1],"ix":4},"o":{"a":0,"k":100,"ix":5},"r":1,"bm":0,"nm":"塗り 1","mn":"ADBE Vector Graphic - Fill","hd":false},{"ty":"tr","p":{"a":0,"k":[49.526,314.603],"ix":2},"a":{"a":0,"k":[0,0],"ix":1},"s":{"a":0,"k":[100,100],"ix":3},"r":{"a":0,"k":0,"ix":6},"o":{"a":0,"k":100,"ix":7},"sk":{"a":0,"k":0,"ix":4},"sa":{"a":0,"k":0,"ix":5},"nm":"トランスフォーム"}],"nm":"グループ 13","np":2,"cix":2,"bm":0,"ix":4,"mn":"ADBE Vector Group","hd":false},{"ty":"gr","it":[{"ind":0,"ty":"sh","ix":1,"ks":{"a":0,"k":{"i":[[0,0],[-1.375,1.02],[-1.043,-1.936],[0,0],[-1.231,-1.074],[0.131,-0.301],[0.55,0.274],[-0.825,-1.375],[0.275,-0.276],[1.151,1.632],[-0.876,-1.907],[0.275,-0.276],[0.95,1.948],[-0.671,-1.798],[0.395,-0.19],[0.508,1.955],[0.193,-1.641],[0.275,0],[0,1.375],[0.275,0.549],[0,1.099],[1.324,1.758]],"o":[[-1.324,-1.757],[1.375,-1.02],[0,0],[1.043,1.938],[1.231,1.074],[-0.131,0.301],[-0.55,-0.276],[0.825,1.375],[-0.275,0.274],[-1.151,-1.632],[0.876,1.907],[-0.275,0.274],[-0.95,-1.949],[0.671,1.798],[-0.395,0.189],[-0.508,-1.956],[-0.193,1.641],[-0.275,0],[0,-1.375],[-0.275,-0.55],[0,-1.101],[0,0]],"v":[[-6.522,-6.008],[-6.429,-11.056],[-2.032,-9.389],[1.175,-3.434],[5.31,2.043],[7.31,4.543],[6.071,4.59],[6.571,6.59],[7.571,9.59],[4.978,7.122],[4.478,7.622],[5.571,11.59],[3.344,8.548],[2.837,8.273],[3.339,11.888],[1.697,8.678],[0.422,8.105],[-0.429,11.09],[-0.929,8.59],[-1.429,5.09],[-1.929,2.09],[-4.336,-3.107]],"c":true},"ix":2},"nm":"パス 1","mn":"ADBE Vector Shape - Group","hd":false},{"ty":"fl","c":{"a":0,"k":[0.885999971278,0.894000004787,0.910000011968,1],"ix":4},"o":{"a":0,"k":100,"ix":5},"r":1,"bm":0,"nm":"塗り 1","mn":"ADBE Vector Graphic - Fill","hd":false},{"ty":"tr","p":{"a":0,"k":[88.661,232.438],"ix":2},"a":{"a":0,"k":[0,0],"ix":1},"s":{"a":0,"k":[100,100],"ix":3},"r":{"a":0,"k":0,"ix":6},"o":{"a":0,"k":100,"ix":7},"sk":{"a":0,"k":0,"ix":4},"sa":{"a":0,"k":0,"ix":5},"nm":"トランスフォーム"}],"nm":"グループ 14","np":2,"cix":2,"bm":0,"ix":5,"mn":"ADBE Vector Group","hd":false},{"ty":"gr","it":[{"ind":0,"ty":"sh","ix":1,"ks":{"a":0,"k":{"i":[[0,0],[0,0],[0.115,-1.622],[0,0],[0,0],[0,0],[0.911,1.888],[0,0],[0,0],[0.765,-1.755],[0,0],[0,0],[0,0],[0.555,2.499],[0,0],[0,0]],"o":[[0,0],[0.446,1.564],[0,0],[0,0],[0,0],[0,-2.096],[0,0],[0,0],[0,1.914],[0,0],[0,0],[0,0],[0.829,-2.423],[0,0],[0,0],[0,0]],"v":[[18.03,-38.5],[25.355,-12.864],[25.855,-8.048],[22.03,45.5],[13.03,45.5],[13.03,9.684],[11.646,3.632],[-0.97,-22.5],[-0.97,0.598],[-2.13,6.16],[-17.97,42.5],[-25.97,41.5],[-14.237,7.204],[-13.819,-0.321],[-20.97,-32.5],[15.03,-45.5]],"c":true},"ix":2},"nm":"パス 1","mn":"ADBE Vector Shape - Group","hd":false},{"ty":"fl","c":{"a":0,"k":[0.054999998504,0.149000010771,0.246999987434,1],"ix":4},"o":{"a":0,"k":100,"ix":5},"r":1,"bm":0,"nm":"塗り 1","mn":"ADBE Vector Graphic - Fill","hd":false},{"ty":"tr","p":{"a":0,"k":[69.702,265.027],"ix":2},"a":{"a":0,"k":[0,0],"ix":1},"s":{"a":0,"k":[100,100],"ix":3},"r":{"a":0,"k":0,"ix":6},"o":{"a":0,"k":100,"ix":7},"sk":{"a":0,"k":0,"ix":4},"sa":{"a":0,"k":0,"ix":5},"nm":"トランスフォーム"}],"nm":"グループ 15","np":2,"cix":2,"bm":0,"ix":6,"mn":"ADBE Vector Group","hd":false},{"ty":"gr","it":[{"ind":0,"ty":"sh","ix":1,"ks":{"a":0,"k":{"i":[[0,0],[2.016,-0.882],[0,0],[0.431,-2.157],[0,0],[-0.861,-2.025],[0,0],[-1.956,0.568],[0,-2.2],[0,0],[-2.2,0],[0,0],[-2.065,0.761],[0,0],[-1.432,1.671],[0,0],[0.875,2.018],[0,0],[0.696,2.087],[0,0],[2.042,0.818]],"o":[[-2.043,-0.817],[0,0],[-2.016,0.881],[0,0],[-0.431,2.158],[0,0],[0.861,2.024],[1.955,-0.567],[0,0],[0,2.2],[0,0],[2.201,0],[0,0],[2.064,-0.761],[0,0],[1.431,-1.67],[0,0],[-0.874,-2.019],[0,0],[-0.696,-2.087],[0,0]],"v":[[-2.281,-40.849],[-9.66,-40.731],[-22.095,-35.29],[-26.544,-29.765],[-34.858,11.802],[-34.076,19.405],[-29.496,30.167],[-24.374,32.815],[-20.819,35.783],[-20.819,37.666],[-16.819,41.666],[1.122,41.666],[8.876,40.283],[24.84,34.401],[31.196,29.981],[33.402,27.408],[34.414,20.701],[21.536,-9.017],[18.681,-16.482],[13.799,-31.128],[8.821,-36.409]],"c":true},"ix":2},"nm":"パス 1","mn":"ADBE Vector Shape - Group","hd":false},{"ty":"fl","c":{"a":0,"k":[0.054999998504,0.149000010771,0.246999987434,1],"ix":4},"o":{"a":0,"k":100,"ix":5},"r":1,"bm":0,"nm":"塗り 1","mn":"ADBE Vector Graphic - Fill","hd":false},{"ty":"tr","p":{"a":0,"k":[63.551,200.862],"ix":2},"a":{"a":0,"k":[0,0],"ix":1},"s":{"a":0,"k":[100,100],"ix":3},"r":{"a":0,"k":0,"ix":6},"o":{"a":0,"k":100,"ix":7},"sk":{"a":0,"k":0,"ix":4},"sa":{"a":0,"k":0,"ix":5},"nm":"トランスフォーム"}],"nm":"グループ 16","np":2,"cix":2,"bm":0,"ix":7,"mn":"ADBE Vector Group","hd":false},{"ty":"gr","it":[{"ind":0,"ty":"sh","ix":1,"ks":{"a":0,"k":{"i":[[39.794,15.768],[-9.385,-23.275],[-33.431,3.003],[18.021,20.648]],"o":[[0,0],[9.386,23.277],[33.431,-3.002],[-18.019,-20.648]],"v":[[-31.091,-26.432],[-141.915,18.348],[-11.357,27.797],[133.279,-20.978]],"c":true},"ix":2},"nm":"パス 1","mn":"ADBE Vector Shape - Group","hd":false},{"ty":"fl","c":{"a":0,"k":[0.961000031116,0.976000019148,0.995999983245,1],"ix":4},"o":{"a":0,"k":100,"ix":5},"r":1,"bm":0,"nm":"塗り 1","mn":"ADBE Vector Graphic - Fill","hd":false},{"ty":"tr","p":{"a":0,"k":[169.823,296.303],"ix":2},"a":{"a":0,"k":[0,0],"ix":1},"s":{"a":0,"k":[100,100],"ix":3},"r":{"a":0,"k":0,"ix":6},"o":{"a":0,"k":100,"ix":7},"sk":{"a":0,"k":0,"ix":4},"sa":{"a":0,"k":0,"ix":5},"nm":"トランスフォーム"}],"nm":"グループ 17","np":2,"cix":2,"bm":0,"ix":8,"mn":"ADBE Vector Group","hd":false},{"ty":"gr","it":[{"ind":0,"ty":"sh","ix":1,"ks":{"a":0,"k":{"i":[[0,-1.224],[0.944,0],[0,1.224],[-0.944,0]],"o":[[0,1.224],[-0.944,0],[0,-1.224],[0.944,0]],"v":[[1.71,0],[0.001,2.216],[-1.71,0],[0.001,-2.216]],"c":true},"ix":2},"nm":"パス 1","mn":"ADBE Vector Shape - Group","hd":false},{"ty":"fl","c":{"a":0,"k":[0.885999971278,0.894000004787,0.910000011968,1],"ix":4},"o":{"a":0,"k":100,"ix":5},"r":1,"bm":0,"nm":"塗り 1","mn":"ADBE Vector Graphic - Fill","hd":false},{"ty":"tr","p":{"a":0,"k":[63.152,147.785],"ix":2},"a":{"a":0,"k":[0,0],"ix":1},"s":{"a":0,"k":[100,100],"ix":3},"r":{"a":0,"k":0,"ix":6},"o":{"a":0,"k":100,"ix":7},"sk":{"a":0,"k":0,"ix":4},"sa":{"a":0,"k":0,"ix":5},"nm":"トランスフォーム"}],"nm":"グループ 18","np":2,"cix":2,"bm":0,"ix":9,"mn":"ADBE Vector Group","hd":false},{"ty":"gr","it":[{"ind":0,"ty":"sh","ix":1,"ks":{"a":0,"k":{"i":[[0,0],[-0.55,-0.013],[0,0],[-0.393,0.386],[0,0],[-0.043,0.548],[0,0],[0.549,-0.033],[0,0],[0.508,-0.212],[0,0],[0.232,-0.498],[0,0],[-0.273,-0.478]],"o":[[0.273,0.478],[0,0],[0.55,0.013],[0,0],[0.392,-0.385],[0,0],[0.043,-0.548],[0,0],[-0.549,0.034],[0,0],[-0.507,0.213],[0,0],[-0.232,0.498],[0,0]],"v":[[-4.949,7.938],[-3.454,8.83],[0.92,8.933],[2.633,8.255],[7.055,3.904],[7.844,2.206],[8.633,-7.977],[7.714,-8.913],[3.868,-8.682],[1.947,-8.235],[-5.171,-5.25],[-6.516,-3.957],[-8.445,0.187],[-8.37,1.961]],"c":true},"ix":2},"nm":"パス 1","mn":"ADBE Vector Shape - Group","hd":false},{"ty":"fl","c":{"a":0,"k":[0.054999998504,0.149000010771,0.246999987434,1],"ix":4},"o":{"a":0,"k":100,"ix":5},"r":1,"bm":0,"nm":"塗り 1","mn":"ADBE Vector Graphic - Fill","hd":false},{"ty":"tr","p":{"a":0,"k":[56.633,143.86],"ix":2},"a":{"a":0,"k":[0,0],"ix":1},"s":{"a":0,"k":[100,100],"ix":3},"r":{"a":0,"k":0,"ix":6},"o":{"a":0,"k":100,"ix":7},"sk":{"a":0,"k":0,"ix":4},"sa":{"a":0,"k":0,"ix":5},"nm":"トランスフォーム"}],"nm":"グループ 19","np":2,"cix":2,"bm":0,"ix":10,"mn":"ADBE Vector Group","hd":false},{"ty":"gr","it":[{"ind":0,"ty":"sh","ix":1,"ks":{"a":0,"k":{"i":[[0,0],[-2.2,0],[0,0],[0.581,2.122],[0,0],[-1.176,0.211],[-0.581,2.122],[0,0],[1.338,1.747],[0,0],[2.197,-0.121],[0,0],[0.591,-2.119],[0,0],[-1.234,-1.821],[0,0],[1.053,-1.931]],"o":[[-1.054,1.931],[0,0],[2.2,0],[0,0],[-0.582,-2.122],[1.176,-0.211],[0,0],[0.581,-2.122],[0,0],[-1.338,-1.747],[0,0],[-2.197,0.121],[0,0],[-0.591,2.119],[0,0],[1.233,1.821],[0,0]],"v":[[-7.283,10.729],[-5.199,14.24],[1.417,14.24],[4.361,10.382],[3.239,6.282],[4.32,2.039],[7.514,-2.204],[7.756,-3.089],[6.38,-10.123],[5.583,-11.164],[-0.842,-14.119],[-1.329,-14.091],[-6.398,-10.017],[-7.206,-7.115],[-6.036,0.049],[-5.743,0.482],[-5.415,7.305]],"c":true},"ix":2},"nm":"パス 1","mn":"ADBE Vector Shape - Group","hd":false},{"ty":"fl","c":{"a":0,"k":[0.885999971278,0.894000004787,0.910000011968,1],"ix":4},"o":{"a":0,"k":100,"ix":5},"r":1,"bm":0,"nm":"塗り 1","mn":"ADBE Vector Graphic - Fill","hd":false},{"ty":"tr","p":{"a":0,"k":[58.707,152.867],"ix":2},"a":{"a":0,"k":[0,0],"ix":1},"s":{"a":0,"k":[100,100],"ix":3},"r":{"a":0,"k":0,"ix":6},"o":{"a":0,"k":100,"ix":7},"sk":{"a":0,"k":0,"ix":4},"sa":{"a":0,"k":0,"ix":5},"nm":"トランスフォーム"}],"nm":"グループ 20","np":2,"cix":2,"bm":0,"ix":11,"mn":"ADBE Vector Group","hd":false},{"ty":"gr","it":[{"ind":0,"ty":"sh","ix":1,"ks":{"a":0,"k":{"i":[[0,0],[-1.621,0.547],[-0.397,-2.164],[0,0],[-0.841,-1.402],[0.217,-0.245],[0.439,0.431],[-0.362,-1.563],[0.346,-0.177],[0.593,1.908],[-0.247,-2.084],[0.346,-0.177],[0.305,2.145],[-0.086,-1.917],[0.434,-0.059],[-0.117,2.017],[0.688,-1.501],[0.261,0.085],[-0.423,1.308],[0.092,0.607],[-0.338,1.047],[0.72,2.079]],"o":[[-0.719,-2.079],[1.622,-0.547],[0,0],[0.396,2.164],[0.842,1.4],[-0.218,0.246],[-0.439,-0.431],[0.363,1.562],[-0.346,0.177],[-0.594,-1.907],[0.247,2.084],[-0.346,0.177],[-0.305,-2.147],[0.086,1.917],[-0.435,0.058],[0.118,-2.017],[-0.688,1.502],[-0.262,-0.084],[0.423,-1.308],[-0.093,-0.608],[0.339,-1.046],[0,0]],"v":[[-4.708,-7.658],[-3.066,-12.434],[0.604,-9.495],[1.824,-2.842],[4.074,3.641],[5.21,6.634],[4.016,6.298],[3.876,8.355],[3.906,11.517],[2.197,8.371],[1.568,8.694],[1.387,12.805],[0.204,9.226],[-0.195,8.81],[-0.827,12.402],[-1.404,8.842],[-2.441,7.906],[-4.168,10.484],[-3.875,7.951],[-3.273,4.467],[-2.827,1.458],[-3.521,-4.224]],"c":true},"ix":2},"nm":"パス 1","mn":"ADBE Vector Shape - Group","hd":false},{"ty":"fl","c":{"a":0,"k":[0.885999971278,0.894000004787,0.910000011968,1],"ix":4},"o":{"a":0,"k":100,"ix":5},"r":1,"bm":0,"nm":"塗り 1","mn":"ADBE Vector Graphic - Fill","hd":false},{"ty":"tr","p":{"a":0,"k":[40.63,240.242],"ix":2},"a":{"a":0,"k":[0,0],"ix":1},"s":{"a":0,"k":[100,100],"ix":3},"r":{"a":0,"k":0,"ix":6},"o":{"a":0,"k":100,"ix":7},"sk":{"a":0,"k":0,"ix":4},"sa":{"a":0,"k":0,"ix":5},"nm":"トランスフォーム"}],"nm":"グループ 21","np":2,"cix":2,"bm":0,"ix":12,"mn":"ADBE Vector Group","hd":false},{"ty":"gr","it":[{"ind":0,"ty":"sh","ix":1,"ks":{"a":0,"k":{"i":[[5.906,0],[0,0],[0,5.907],[0,0],[-5.907,0],[0,0],[0,-5.906],[0,0]],"o":[[0,0],[-5.907,0],[0,0],[0,-5.906],[0,0],[5.906,0],[0,0],[0,5.907]],"v":[[109.306,91.5],[-109.305,91.5],[-120,80.805],[-120,-80.806],[-109.305,-91.5],[109.306,-91.5],[120,-80.806],[120,80.805]],"c":true},"ix":2},"nm":"パス 1","mn":"ADBE Vector Shape - Group","hd":false},{"ty":"fl","c":{"a":0,"k":[0.961000031116,0.976000019148,0.995999983245,1],"ix":4},"o":{"a":0,"k":100,"ix":5},"r":1,"bm":0,"nm":"塗り 1","mn":"ADBE Vector Graphic - Fill","hd":false},{"ty":"tr","p":{"a":0,"k":[199.732,109.027],"ix":2},"a":{"a":0,"k":[0,0],"ix":1},"s":{"a":0,"k":[100,100],"ix":3},"r":{"a":0,"k":0,"ix":6},"o":{"a":0,"k":100,"ix":7},"sk":{"a":0,"k":0,"ix":4},"sa":{"a":0,"k":0,"ix":5},"nm":"トランスフォーム"}],"nm":"グループ 22","np":2,"cix":2,"bm":0,"ix":13,"mn":"ADBE Vector Group","hd":false}],"ip":0,"op":60.0000024438501,"st":0,"bm":0}],"markers":[]}